sp.py
lib/BaseConnection.py
lib/__init__.py
lib/appliance.py
lib/bgp.py
lib/flows.py
lib/orch.py
lib/ospf.py
lib/parser.py
lib/qos.py
pyspcli-0.1.3.dist-info/LICENSE
pyspcli-0.1.3.dist-info/METADATA
pyspcli-0.1.3.dist-info/WHEEL
pyspcli-0.1.3.dist-info/entry_points.txt
pyspcli-0.1.3.dist-info/top_level.txt
pyspcli-0.1.3.dist-info/RECORD
