Metadata-Version: 2.1
Name: pyspcli
Version: 0.1.3
Summary: Silverpeak SD-WAN Command Line Interface
Home-page: https://github.com/ipHeaders/spcli
Author: IP Headers.llc
Author-email: kentik.hanzo94@gmail.com
Project-URL: Bug Tracker, https://github.com/ipHeaders/spcli/issues
Project-URL: Code of Conduct, https://github.com/ipHeaders/spcli/blob/main/CODE_OF_CONDUCT.md
Project-URL: Source Code, https://github.com/ipHeaders/spcli
Classifier: Intended Audience :: Developers
Classifier: Intended Audience :: Information Technology
Classifier: Intended Audience :: System Administrators
Classifier: Natural Language :: English
Classifier: Programming Language :: Python :: 3
Classifier: Programming Language :: Python :: 3.7
Classifier: Programming Language :: Python :: 3.8
Classifier: Programming Language :: Python :: 3.9
Classifier: Programming Language :: Python :: 3.10
Classifier: Programming Language :: Python :: 3.11
Classifier: Programming Language :: Python :: 3 :: Only
Requires-Python: >=3.7, <4
License-File: LICENSE
Requires-Dist: pyedgeconnect
Requires-Dist: importlib-metadata
Requires-Dist: PyYAML (==6.0)
Requires-Dist: tabulate (==0.8.10)
